{
  "version": "1.0",
  "commands": [
    {
      "id": "file-ops",
      "label": "ファイル操作",
      "children": [
        {
          "id": "file-basic",
          "label": "基本操作",
          "children": [
            {
              "id": "ls",
              "label": "List Files",
              "command": "ls -la\n",
              "description": "ls [-l] [-a] [ディレクトリ] - ディレクトリ内容をリスト表示"
            },
            {
              "id": "pwd",
              "label": "Current Directory",
              "command": "pwd\n",
              "description": "pwd - 現在のディレクトリパスを表示"
            },
            {
              "id": "cd",
              "label": "Change Directory",
              "command": "cd ",
              "description": "cd [ディレクトリ] - 指定ディレクトリに移動"
            }
          ]
        },
        {
          "id": "file-view",
          "label": "ファイル表示",
          "children": [
            {
              "id": "cat",
              "label": "View File Contents",
              "command": "cat ",
              "description": "cat [ファイル名] - ファイルの内容を表示"
            },
            {
              "id": "less",
              "label": "View with Pager",
              "command": "less ",
              "description": "less [ファイル名] - ファイルを1画面ずつ表示"
            },
            {
              "id": "head",
              "label": "View File Head",
              "command": "head ",
              "description": "head [-n 行数] [ファイル名] - ファイルの先頭部分を表示"
            },
            {
              "id": "tail",
              "label": "View File Tail",
              "command": "tail ",
              "description": "tail [-n 行数] [ファイル名] - ファイルの末尾部分を表示"
            }
          ]
        },
        {
          "id": "file-manage",
          "label": "ファイル管理",
          "children": [
            {
              "id": "cp",
              "label": "Copy File",
              "command": "cp ",
              "description": "cp [コピー元] [コピー先] - ファイルをコピー"
            },
            {
              "id": "mv",
              "label": "Move/Rename File",
              "command": "mv ",
              "description": "mv [移動元] [移動先] - ファイルを移動/名前変更"
            },
            {
              "id": "rm",
              "label": "Remove File",
              "command": "rm ",
              "description": "rm [-r] [ファイル名] - ファイル/ディレクトリを削除"
            }
          ]
        },
        {
          "id": "file-perm",
          "label": "権限管理",
          "children": [
            {
              "id": "chmod",
              "label": "Change Permissions",
              "command": "chmod ",
              "description": "chmod [モード] [ファイル名] - ファイルの権限を変更"
            },
            {
              "id": "chown",
              "label": "Change Owner",
              "command": "chown ",
              "description": "chown [ユーザー:グループ] [ファイル名] - 所有者を変更"
            }
          ]
        }
      ]
    },
    {
      "id": "process-ops",
      "label": "プロセス管理",
      "children": [
        {
          "id": "ps",
          "label": "List Processes",
          "command": "ps\n",
          "description": "ps [-ef] - 実行中のプロセスを表示"
        },
        {
          "id": "top",
          "label": "System Monitor",
          "command": "top\n",
          "description": "top - システムの状態をリアルタイムで表示"
        },
        {
          "id": "kill",
          "label": "Kill Process",
          "command": "kill ",
          "description": "kill [-9] [プロセスID] - プロセスを終了"
        }
      ]
    },
    {
      "id": "system-ops",
      "label": "システム情報",
      "children": [
        {
          "id": "df",
          "label": "Disk Usage",
          "command": "df\n",
          "description": "df [-h] - ディスクの使用状況を表示"
        },
        {
          "id": "free",
          "label": "Memory Usage",
          "command": "free\n",
          "description": "free [-h] - メモリの使用状況を表示"
        },
        {
          "id": "date",
          "label": "Current Date",
          "command": "date\n",
          "description": "date - システムの日時を表示"
        }
      ]
    },
    {
      "id": "text-ops",
      "label": "テキスト処理",
      "children": [
        {
          "id": "grep",
          "label": "Search Text",
          "command": "grep ",
          "description": "grep [検索パターン] [ファイル名] - ファイル内の文字列を検索"
        },
        {
          "id": "wc",
          "label": "Count Words",
          "command": "wc ",
          "description": "wc [-l] [-w] [-c] [ファイル名] - 行数・単語数・文字数をカウント"
        },
        {
          "id": "find",
          "label": "Find Files",
          "command": "find ",
          "description": "find [検索開始ディレクトリ] -name [ファイル名] - ファイルを検索"
        }
      ]
    },
    {
      "id": "network-ops",
      "label": "ネットワーク",
      "children": [
        {
          "id": "ping",
          "label": "Test Connection",
          "command": "ping ",
          "description": "ping [ホスト名/IPアドレス] - ホストとの疎通を確認"
        },
        {
          "id": "ifconfig",
          "label": "Network Config",
          "command": "ifconfig\n",
          "description": "ifconfig - ネットワークインターフェースの設定を表示"
        },
        {
          "id": "netstat",
          "label": "Network Status",
          "command": "netstat ",
          "description": "netstat [-an] - ネットワーク接続状態を表示"
        }
      ]
    }
  ]
}
